py_dev_deps/__init__.py
py_dev_deps-0.5.0.dist-info/LICENSE
py_dev_deps-0.5.0.dist-info/WHEEL
py_dev_deps-0.5.0.dist-info/METADATA
py_dev_deps-0.5.0.dist-info/RECORD
